voicechangerio/__init__.py
voicechangerio/errors.py
voicechangerio/models.py
voicechangerio/voicechangerio.py
voicechangerio-0.2.0.dist-info/LICENSE.txt
voicechangerio-0.2.0.dist-info/METADATA
voicechangerio-0.2.0.dist-info/WHEEL
voicechangerio-0.2.0.dist-info/RECORD
