Metadata-Version: 2.1
Name: voicechangerio
Version: 0.2.0
Summary: VoiceChangerIO is a Python library that provides an interface to the voice transformation functionality of the VoiceChanger.io website. It allows you to apply various voice effects to audio files programmatically using a web browser automation approach.
License: MPL-2.0
Author: Eugene
Author-email: orion25rus@gmail.com
Requires-Python: >=3.7,<4.0
Classifier: License :: OSI Approved
Classifier: Programming Language :: Python :: 3
Classifier: Programming Language :: Python :: 3.7
Classifier: Programming Language :: Python :: 3.8
Classifier: Programming Language :: Python :: 3.9
Classifier: Programming Language :: Python :: 3.10
Classifier: Programming Language :: Python :: 3.11
Requires-Dist: pydantic (>=2.0,<3.0)
Requires-Dist: selenium (>=4.10.0,<5.0.0)
